coolcsv/__init__.py
coolcsv/mydb.py
coolcsv-0.0.1.dist-info/LICENSE
coolcsv-0.0.1.dist-info/METADATA
coolcsv-0.0.1.dist-info/WHEEL
coolcsv-0.0.1.dist-info/top_level.txt
coolcsv-0.0.1.dist-info/RECORD
