Metadata-Version: 2.1
Name: coolcsv
Version: 0.0.1
Summary: rapid database build using csv
Author-email: Aston kariuki <astonmwendwa254@gmail.com>
Classifier: Programming Language :: Python :: 3
Classifier: License :: OSI Approved :: MIT License
Classifier: Operating System :: OS Independent
Requires-Python: >=3.8
License-File: LICENSE
